mocanexion/__init__.py
mocanexion-1.1.0.dist-info/LICENSE.txt
mocanexion-1.1.0.dist-info/METADATA
mocanexion-1.1.0.dist-info/WHEEL
mocanexion-1.1.0.dist-info/top_level.txt
mocanexion-1.1.0.dist-info/RECORD
